.gitignore
.travis.yml
MANIFEST.in
README.txt
bootstrap.py
buildout.cfg
setup.py
travis.cfg
collective/__init__.py
collective.local.sendto.egg-info/PKG-INFO
collective.local.sendto.egg-info/SOURCES.txt
collective.local.sendto.egg-info/dependency_links.txt
collective.local.sendto.egg-info/entry_points.txt
collective.local.sendto.egg-info/namespace_packages.txt
collective.local.sendto.egg-info/not-zip-safe
collective.local.sendto.egg-info/requires.txt
collective.local.sendto.egg-info/top_level.txt
collective/local/__init__.py
collective/local/sendto/__init__.py
collective/local/sendto/configure.zcml
collective/local/sendto/dexterity.zcml
collective/local/sendto/events.py
collective/local/sendto/interfaces.py
collective/local/sendto/testing.py
collective/local/sendto/testing.zcml
collective/local/sendto/upgrades.py
collective/local/sendto/utils.py
collective/local/sendto/browser/__init__.py
collective/local/sendto/browser/configure.zcml
collective/local/sendto/browser/send.py
collective/local/sendto/browser/view.py
collective/local/sendto/browser/templates/collective_sendto.pt
collective/local/sendto/locales/collective.local.sendto.pot
collective/local/sendto/locales/update.sh
collective/local/sendto/locales/da/LC_MESSAGES/collective.local.sendto.po
collective/local/sendto/locales/de/LC_MESSAGES/collective.local.sendto.po
collective/local/sendto/locales/es/LC_MESSAGES/collective.local.sendto.po
collective/local/sendto/locales/fi/LC_MESSAGES/collective.local.sendto.po
collective/local/sendto/locales/fr/LC_MESSAGES/collective.local.sendto.po
collective/local/sendto/locales/it/LC_MESSAGES/collective.local.sendto.po
collective/local/sendto/locales/no/LC_MESSAGES/collective.local.sendto.po
collective/local/sendto/locales/pt/LC_MESSAGES/collective.local.sendto.po
collective/local/sendto/locales/zh_CN/LC_MESSAGES/collective.local.sendto.po
collective/local/sendto/locales/zh_TW/LC_MESSAGES/collective.local.sendto.po
collective/local/sendto/profiles/default/actions.xml
collective/local/sendto/profiles/default/metadata.xml
collective/local/sendto/profiles/default/propertiestool.xml
collective/local/sendto/profiles/default/rolemap.xml
collective/local/sendto/profiles/default/skins.xml
collective/local/sendto/profiles/testing/metadata.xml
collective/local/sendto/skins/collective_sendto/collective_sendto_template.pt
collective/local/sendto/tests/__init__.py
