Metadata-Version: 1.1
Name: collective.local.sendto
Version: 1.6
Summary: Adds a 'Mailing' tab to selected content types that allows to select users that have a role on the content and send them a wysiwyg composed email. By Ecreall.
Home-page: http://svn.plone.org/svn/collective/
Author: Thomas Desvenain
Author-email: thomas.desvenain@gmail.com
License: GPL
Keywords: communication,auth
Platform: UNKNOWN
Classifier: Framework :: Plone
Classifier: Programming Language :: Python
